{
    "mse": [
        0.007059721427208548,
        0.00896775424537302,
        0.004742824433723117
    ],
    "mae": [
        0.0013356229727151307,
        0.0015536838662196417,
        0.001035789244146428
    ],
    "rmse": [
        0.08402214843247313,
        0.09469822725570431,
        0.06886816705650817
    ],
    "r2": [
        0.9250028070869011,
        0.8710946836473057,
        0.9156211827519964
    ],
    "accuracy": [
        0.9994275901545506,
        0.9993730749311746,
        0.999563878212991
    ],
    "precision": [
        0.9995536385523661,
        0.9994527254973127,
        0.9996267532203917
    ],
    "recall": [
        0.9994275901545506,
        0.9993730749311746,
        0.999563878212991
    ],
    "f1": [
        0.9994537976066556,
        0.9993860808456919,
        0.9995650321097582
    ],
    "confusion_matrices": [
        [
            [
                36616,
                3,
                0,
                1,
                0,
                0,
                0,
                0,
                0,
                0,
                1
            ],
            [
                1,
                10,
                0,
                0,
                0,
                0,
                0,
                0,
                0,
                0,
                0
            ],
            [
                0,
                0,
                8,
                1,
                0,
                0,
                0,
                0,
                0,
                0,
                0
            ],
            [
                0,
                0,
                1,
                2,
                2,
                0,
                0,
                0,
                0,
                0,
                0
            ],
            [
                0,
                0,
                0,
                0,
                0,
                0,
                0,
                0,
                0,
                0,
                0
            ],
            [
                0,
                0,
                0,
                0,
                0,
                1,
                2,
                0,
                0,
                1,
                0
            ],
            [
                0,
                0,
                0,
                0,
                0,
                0,
                1,
                1,
                1,
                1,
                0
            ],
            [
                0,
                0,
                0,
                0,
                0,
                0,
                0,
                1,
                0,
                0,
                0
            ],
            [
                0,
                0,
                0,
                0,
                0,
                0,
                1,
                0,
                0,
                2,
                0
            ],
            [
                0,
                0,
                0,
                0,
                0,
                0,
                0,
                0,
                0,
                1,
                0
            ],
            [
                1,
                0,
                0,
                0,
                0,
                0,
                0,
                0,
                1,
                0,
                26
            ]
        ],
        [
            [
                36628,
                0,
                1,
                1,
                0,
                0,
                0,
                0,
                0,
                1,
                1
            ],
            [
                0,
                8,
                1,
                0,
                0,
                0,
                0,
                0,
                0,
                0,
                0
            ],
            [
                0,
                0,
                7,
                0,
                0,
                0,
                0,
                0,
                0,
                0,
                0
            ],
            [
                0,
                0,
                1,
                2,
                3,
                0,
                0,
                0,
                0,
                0,
                0
            ],
            [
                0,
                0,
                0,
                0,
                2,
                0,
                0,
                0,
                0,
                0,
                0
            ],
            [
                0,
                0,
                0,
                0,
                0,
                0,
                2,
                1,
                1,
                0,
                0
            ],
            [
                0,
                0,
                0,
                0,
                0,
                0,
                0,
                2,
                1,
                0,
                0
            ],
            [
                0,
                0,
                0,
                0,
                0,
                0,
                0,
                0,
                1,
                1,
                0
            ],
            [
                0,
                0,
                0,
                0,
                0,
                0,
                0,
                0,
                0,
                1,
                0
            ],
            [
                0,
                0,
                0,
                0,
                0,
                0,
                0,
                0,
                0,
                1,
                1
            ],
            [
                1,
                0,
                0,
                0,
                0,
                0,
                0,
                0,
                0,
                2,
                16
            ]
        ],
        [
            [
                36639,
                1,
                0,
                0,
                0,
                0,
                0,
                0,
                0,
                0,
                1
            ],
            [
                1,
                5,
                1,
                0,
                0,
                0,
                0,
                0,
                0,
                0,
                0
            ],
            [
                0,
                0,
                5,
                0,
                0,
                0,
                0,
                0,
                0,
                0,
                0
            ],
            [
                0,
                0,
                1,
                2,
                0,
                1,
                1,
                0,
                0,
                0,
                0
            ],
            [
                0,
                0,
                0,
                0,
                3,
                0,
                0,
                0,
                0,
                1,
                0
            ],
            [
                0,
                0,
                0,
                0,
                0,
                1,
                1,
                1,
                0,
                1,
                0
            ],
            [
                0,
                0,
                0,
                0,
                0,
                0,
                0,
                0,
                1,
                0,
                0
            ],
            [
                0,
                0,
                0,
                0,
                0,
                1,
                1,
                0,
                1,
                0,
                0
            ],
            [
                0,
                0,
                0,
                0,
                0,
                0,
                0,
                0,
                1,
                0,
                0
            ],
            [
                0,
                0,
                0,
                0,
                0,
                0,
                0,
                0,
                0,
                0,
                1
            ],
            [
                0,
                0,
                0,
                0,
                0,
                0,
                0,
                0,
                0,
                0,
                15
            ]
        ]
    ]
}